bschemistry/__init__.py
bschemistry-0.1.2.dist-info/METADATA
bschemistry-0.1.2.dist-info/WHEEL
bschemistry-0.1.2.dist-info/licenses/LICENSE
bschemistry-0.1.2.dist-info/RECORD
